[
    {
        "handedness": {
            "index": 1,
            "score": 0.9437465071678162,
            "label": "Right"
        },
        "landmarks": [
            {
                "name": "WRIST",
                "x": 0.3489088714122772,
                "y": 0.8180768489837646,
                "z": 8.722204825062363e-07
            },
            {
                "name": "THUMP_CMC",
                "x": 0.4975475072860718,
                "y": 0.7426320910453796,
                "z": -0.003506363369524479
            },
            {
                "name": "THUMB_MCP",
                "x": 0.5659219622612,
                "y": 0.6526768803596497,
                "z": -0.0013205703580752015
            },
            {
                "name": "THUMB_IP",
                "x": 0.566631019115448,
                "y": 0.5765387415885925,
                "z": 0.029158513993024826
            },
            {
                "name": "THUMB_TIP",
                "x": 0.5156819820404053,
                "y": 0.526604175567627,
                "z": 0.07684016227722168
            },
            {
                "name": "INDEX_FINGER_MCP",
                "x": 0.43606558442115784,
                "y": 0.5740468502044678,
                "z": -0.1550346165895462
            },
            {
                "name": "INDEX_FINGER_PIP",
                "x": 0.4991706311702728,
                "y": 0.4748137593269348,
                "z": -0.1037805899977684
            },
            {
                "name": "INDEX_FINGER_DIP",
                "x": 0.5123397707939148,
                "y": 0.5136950612068176,
                "z": -0.02506079338490963
            },
            {
                "name": "INDEX_FINGER_TIP",
                "x": 0.48942258954048157,
                "y": 0.5495032072067261,
                "z": 0.030351407825946808
            },
            {
                "name": "MIDDLE_FINGER_MCP",
                "x": 0.33924123644828796,
                "y": 0.5638570785522461,
                "z": -0.11823868751525879
            },
            {
                "name": "MIDDLE_FINGER_PIP",
                "x": 0.409671425819397,
                "y": 0.423780620098114,
                "z": -0.12464650720357895
            },
            {
                "name": "MIDDLE_FINGER_DIP",
                "x": 0.44890451431274414,
                "y": 0.3485647439956665,
                "z": -0.0992569550871849
            },
            {
                "name": "MIDDLE_FINGER_TIP",
                "x": 0.4633171856403351,
                "y": 0.29233500361442566,
                "z": -0.08281632512807846
            },
            {
                "name": "RING_FINGER_MCP",
                "x": 0.2572154402732849,
                "y": 0.5664394497871399,
                "z": -0.05373429134488106
            },
            {
                "name": "RING_FINGER_PIP",
                "x": 0.3311503827571869,
                "y": 0.4676213562488556,
                "z": -0.023199843242764473
            },
            {
                "name": "RING_FINGER_DIP",
                "x": 0.36216413974761963,
                "y": 0.49637526273727417,
                "z": 0.02487397938966751
            },
            {
                "name": "RING_FINGER_TIP",
                "x": 0.3654648959636688,
                "y": 0.5375556349754333,
                "z": 0.0521954782307148
            },
            {
                "name": "PINKY_MCP",
                "x": 0.19307218492031097,
                "y": 0.5803741216659546,
                "z": 0.016344992443919182
            },
            {
                "name": "PINKY_PIP",
                "x": 0.24938933551311493,
                "y": 0.4923286736011505,
                "z": 0.06964839994907379
            },
            {
                "name": "PINKY_DIP",
                "x": 0.2828149199485779,
                "y": 0.5109893679618835,
                "z": 0.12692321836948395
            },
            {
                "name": "PINKY_TIP",
                "x": 0.29788684844970703,
                "y": 0.5442723631858826,
                "z": 0.16304649412631989
            }
        ]
    }
]