[
    {
        "handedness": {
            "index": 0,
            "score": 0.8987441062927246,
            "label": "Left"
        },
        "landmarks": [
            {
                "name": "WRIST",
                "x": 0.6999322772026062,
                "y": 0.8266366124153137,
                "z": -1.469031644774077e-06
            },
            {
                "name": "THUMP_CMC",
                "x": 0.43626368045806885,
                "y": 0.7914752960205078,
                "z": 0.10367342829704285
            },
            {
                "name": "THUMB_MCP",
                "x": 0.2938023805618286,
                "y": 0.6971779465675354,
                "z": 0.1970580369234085
            },
            {
                "name": "THUMB_IP",
                "x": 0.2042955458164215,
                "y": 0.6481918096542358,
                "z": 0.2767126262187958
            },
            {
                "name": "THUMB_TIP",
                "x": 0.18647989630699158,
                "y": 0.6188687086105347,
                "z": 0.3594658374786377
            },
            {
                "name": "INDEX_FINGER_MCP",
                "x": 0.42874079942703247,
                "y": 0.5273769497871399,
                "z": 0.24984191358089447
            },
            {
                "name": "INDEX_FINGER_PIP",
                "x": 0.28405940532684326,
                "y": 0.5242993831634521,
                "z": 0.3184215724468231
            },
            {
                "name": "INDEX_FINGER_DIP",
                "x": 0.28475725650787354,
                "y": 0.5952070951461792,
                "z": 0.31318235397338867
            },
            {
                "name": "INDEX_FINGER_TIP",
                "x": 0.3020474910736084,
                "y": 0.6023411154747009,
                "z": 0.3049369156360626
            },
            {
                "name": "MIDDLE_FINGER_MCP",
                "x": 0.4794863760471344,
                "y": 0.5219877362251282,
                "z": 0.22138971090316772
            },
            {
                "name": "MIDDLE_FINGER_PIP",
                "x": 0.2685733139514923,
                "y": 0.5401780605316162,
                "z": 0.27910903096199036
            },
            {
                "name": "MIDDLE_FINGER_DIP",
                "x": 0.2515939772129059,
                "y": 0.6396124362945557,
                "z": 0.22568149864673615
            },
            {
                "name": "MIDDLE_FINGER_TIP",
                "x": 0.2820013165473938,
                "y": 0.6714668273925781,
                "z": 0.18803808093070984
            },
            {
                "name": "RING_FINGER_MCP",
                "x": 0.48667532205581665,
                "y": 0.5125212073326111,
                "z": 0.19909854233264923
            },
            {
                "name": "RING_FINGER_PIP",
                "x": 0.2801554799079895,
                "y": 0.5257933735847473,
                "z": 0.2734588086605072
            },
            {
                "name": "RING_FINGER_DIP",
                "x": 0.2528994083404541,
                "y": 0.6235468983650208,
                "z": 0.23781093955039978
            },
            {
                "name": "RING_FINGER_TIP",
                "x": 0.28417372703552246,
                "y": 0.6571613550186157,
                "z": 0.20652654767036438
            },
            {
                "name": "PINKY_MCP",
                "x": 0.502409040927887,
                "y": 0.5123791098594666,
                "z": 0.1852877289056778
            },
            {
                "name": "PINKY_PIP",
                "x": 0.4552837014198303,
                "y": 0.37736696004867554,
                "z": 0.26797887682914734
            },
            {
                "name": "PINKY_DIP",
                "x": 0.45396509766578674,
                "y": 0.302935391664505,
                "z": 0.2884424924850464
            },
            {
                "name": "PINKY_TIP",
                "x": 0.46696382761001587,
                "y": 0.24028418958187103,
                "z": 0.29464882612228394
            }
        ]
    }
]