[
    {
        "handedness": {
            "index": 1,
            "score": 0.9919284582138062,
            "label": "Right"
        },
        "landmarks": [
            {
                "name": "WRIST",
                "x": 0,
                "y": 1.0106573104858398,
                "z": 0
            },
            {
                "name": "THUMP_CMC",
                "x": 0,
                "y": 0.9988015294075012,
                "z": 0
            },
            {
                "name": "THUMB_MCP",
                "x": 0,
                "y": 0.8739999532699585,
                "z": 0
            },
            {
                "name": "THUMB_IP",
                "x": 0,
                "y": 0.737644612789154,
                "z": 0
            },
            {
                "name": "THUMB_TIP",
                "x": 0,
                "y": 0.619504451751709,
                "z": 0
            },
            {
                "name": "INDEX_FINGER_MCP",
                "x": 0,
                "y": 0.7034478187561035,
                "z": 0
            },
            {
                "name": "INDEX_FINGER_PIP",
                "x": 0,
                "y": 0.5831918120384216,
                "z": 0
            },
            {
                "name": "INDEX_FINGER_DIP",
                "x": 0,
                "y": 0.547071635723114,
                "z": 0
            },
            {
                "name": "INDEX_FINGER_TIP",
                "x": 0,
                "y": 0.5514294505119324,
                "z": 0
            },
            {
                "name": "MIDDLE_FINGER_MCP",
                "x": 0,
                "y": 0.6965574026107788,
                "z": 0
            },
            {
                "name": "MIDDLE_FINGER_PIP",
                "x": 0,
                "y": 0.6135404706001282,
                "z": 0
            },
            {
                "name": "MIDDLE_FINGER_DIP",
                "x": 0,
                "y": 0.7639716267585754,
                "z": 0
            },
            {
                "name": "MIDDLE_FINGER_TIP",
                "x": 0,
                "y": 0.880942702293396,
                "z": 0
            },
            {
                "name": "RING_FINGER_MCP",
                "x": 0,
                "y": 0.7163879871368408,
                "z": 0
            },
            {
                "name": "RING_FINGER_PIP",
                "x": 0,
                "y": 0.6442121863365173,
                "z": 0
            },
            {
                "name": "RING_FINGER_DIP",
                "x": 0,
                "y": 0.797545313835144,
                "z": 0
            },
            {
                "name": "RING_FINGER_TIP",
                "x": 0,
                "y": 0.9103028774261475,
                "z": 0
            },
            {
                "name": "PINKY_MCP",
                "x": 0,
                "y": 0.7565757036209106,
                "z": 0
            },
            {
                "name": "PINKY_PIP",
                "x": 0,
                "y": 0.6998118758201599,
                "z": 0
            },
            {
                "name": "PINKY_DIP",
                "x": 0,
                "y": 0.8085083961486816,
                "z": 0
            },
            {
                "name": "PINKY_TIP",
                "x": 0,
                "y": 0.8938741683959961,
                "z": 0
            }
        ]
    }
]