[
    {
        "handedness": {
            "index": 1,
            "score": 0.9685426950454712,
            "label": "Right"
        },
        "landmarks": [
            {
                "name": "WRIST",
                "x": 0.26918381452560425,
                "y": 0.5488559007644653,
                "z": 3.4712931551439397e-07
            },
            {
                "name": "THUMP_CMC",
                "x": 0.44141119718551636,
                "y": 0.5220621824264526,
                "z": 0.02312423288822174
            },
            {
                "name": "THUMB_MCP",
                "x": 0.5304065942764282,
                "y": 0.47884601354599,
                "z": 0.06095514073967934
            },
            {
                "name": "THUMB_IP",
                "x": 0.5582926273345947,
                "y": 0.42450717091560364,
                "z": 0.1217658668756485
            },
            {
                "name": "THUMB_TIP",
                "x": 0.4996104836463928,
                "y": 0.3993107080459595,
                "z": 0.20089885592460632
            },
            {
                "name": "INDEX_FINGER_MCP",
                "x": 0.41414064168930054,
                "y": 0.3027883470058441,
                "z": -0.04424966499209404
            },
            {
                "name": "INDEX_FINGER_PIP",
                "x": 0.44451481103897095,
                "y": 0.20934224128723145,
                "z": 0.014116017147898674
            },
            {
                "name": "INDEX_FINGER_DIP",
                "x": 0.47694531083106995,
                "y": 0.1964120864868164,
                "z": 0.11655429005622864
            },
            {
                "name": "INDEX_FINGER_TIP",
                "x": 0.4726342260837555,
                "y": 0.23619800806045532,
                "z": 0.20496416091918945
            },
            {
                "name": "MIDDLE_FINGER_MCP",
                "x": 0.31727108359336853,
                "y": 0.3002433478832245,
                "z": 0.0067716073244810104
            },
            {
                "name": "MIDDLE_FINGER_PIP",
                "x": 0.3136403262615204,
                "y": 0.1712842881679535,
                "z": 0.031312767416238785
            },
            {
                "name": "MIDDLE_FINGER_DIP",
                "x": 0.3485284447669983,
                "y": 0.164730042219162,
                "z": 0.12202434241771698
            },
            {
                "name": "MIDDLE_FINGER_TIP",
                "x": 0.3622579276561737,
                "y": 0.2058017998933792,
                "z": 0.2081376016139984
            },
            {
                "name": "RING_FINGER_MCP",
                "x": 0.23933760821819305,
                "y": 0.319125235080719,
                "z": 0.07276169955730438
            },
            {
                "name": "RING_FINGER_PIP",
                "x": 0.22196799516677856,
                "y": 0.20242434740066528,
                "z": 0.09468930959701538
            },
            {
                "name": "RING_FINGER_DIP",
                "x": 0.2590022385120392,
                "y": 0.1927519291639328,
                "z": 0.16710573434829712
            },
            {
                "name": "RING_FINGER_TIP",
                "x": 0.2850642204284668,
                "y": 0.2238607108592987,
                "z": 0.23782917857170105
            },
            {
                "name": "PINKY_MCP",
                "x": 0.18277935683727264,
                "y": 0.34847331047058105,
                "z": 0.14877943694591522
            },
            {
                "name": "PINKY_PIP",
                "x": 0.14874109625816345,
                "y": 0.26542943716049194,
                "z": 0.1731896698474884
            },
            {
                "name": "PINKY_DIP",
                "x": 0.17863111197948456,
                "y": 0.2465636283159256,
                "z": 0.20774789154529572
            },
            {
                "name": "PINKY_TIP",
                "x": 0.2135697305202484,
                "y": 0.25908321142196655,
                "z": 0.24967943131923676
            }
        ]
    }
]