[
    {
        "handedness": {
            "index": 0,
            "score": 0.5861238241195679,
            "label": "Left"
        },
        "landmarks": [
            {
                "name": "WRIST",
                "x": 0.1935146450996399,
                "y": 0.6681991815567017,
                "z": 1.3189207948016701e-06
            },
            {
                "name": "THUMP_CMC",
                "x": 0.2000124454498291,
                "y": 0.6223586201667786,
                "z": -0.15711373090744019
            },
            {
                "name": "THUMB_MCP",
                "x": 0.20369231700897217,
                "y": 0.5239241719245911,
                "z": -0.19416040182113647
            },
            {
                "name": "THUMB_IP",
                "x": 0.21805652976036072,
                "y": 0.41890761256217957,
                "z": -0.19461491703987122
            },
            {
                "name": "THUMB_TIP",
                "x": 0.27804625034332275,
                "y": 0.34975117444992065,
                "z": -0.1854003667831421
            },
            {
                "name": "INDEX_FINGER_MCP",
                "x": 0.28795069456100464,
                "y": 0.4468939006328583,
                "z": -0.086101233959198
            },
            {
                "name": "INDEX_FINGER_PIP",
                "x": 0.43553879857063293,
                "y": 0.3999931514263153,
                "z": -0.10695122182369232
            },
            {
                "name": "INDEX_FINGER_DIP",
                "x": 0.5332679748535156,
                "y": 0.3968992233276367,
                "z": -0.12792560458183289
            },
            {
                "name": "INDEX_FINGER_TIP",
                "x": 0.6200522184371948,
                "y": 0.3963952958583832,
                "z": -0.1406875103712082
            },
            {
                "name": "MIDDLE_FINGER_MCP",
                "x": 0.2949550449848175,
                "y": 0.4414454996585846,
                "z": 0.002326114336028695
            },
            {
                "name": "MIDDLE_FINGER_PIP",
                "x": 0.43562328815460205,
                "y": 0.391044944524765,
                "z": -0.020031828433275223
            },
            {
                "name": "MIDDLE_FINGER_DIP",
                "x": 0.5235146284103394,
                "y": 0.3942948877811432,
                "z": -0.03968145698308945
            },
            {
                "name": "MIDDLE_FINGER_TIP",
                "x": 0.6055331230163574,
                "y": 0.39633992314338684,
                "z": -0.04815077781677246
            },
            {
                "name": "RING_FINGER_MCP",
                "x": 0.29454997181892395,
                "y": 0.44954371452331543,
                "z": 0.07680272310972214
            },
            {
                "name": "RING_FINGER_PIP",
                "x": 0.37822088599205017,
                "y": 0.41272085905075073,
                "z": 0.046605776995420456
            },
            {
                "name": "RING_FINGER_DIP",
                "x": 0.41614586114883423,
                "y": 0.41648754477500916,
                "z": 0.023777132853865623
            },
            {
                "name": "RING_FINGER_TIP",
                "x": 0.45601773262023926,
                "y": 0.4201471209526062,
                "z": 0.017429787665605545
            },
            {
                "name": "PINKY_MCP",
                "x": 0.2955397069454193,
                "y": 0.4574691951274872,
                "z": 0.13940146565437317
            },
            {
                "name": "PINKY_PIP",
                "x": 0.3313276171684265,
                "y": 0.4299840033054352,
                "z": 0.10901995748281479
            },
            {
                "name": "PINKY_DIP",
                "x": 0.34630781412124634,
                "y": 0.4300655722618103,
                "z": 0.08879122883081436
            },
            {
                "name": "PINKY_TIP",
                "x": 0.36903315782546997,
                "y": 0.42287155985832214,
                "z": 0.08214078843593597
            }
        ]
    }
]