[
    {
        "handedness": {
            "index": 1,
            "score": 0.7922608256340027,
            "label": "Right"
        },
        "landmarks": [
            {
                "name": "WRIST",
                "x": 0.44147971272468567,
                "y": 0.7620297074317932,
                "z": 1.6905828488233965e-06
            },
            {
                "name": "THUMP_CMC",
                "x": 0.4916655123233795,
                "y": 0.6289421319961548,
                "z": -0.14868424832820892
            },
            {
                "name": "THUMB_MCP",
                "x": 0.5428903102874756,
                "y": 0.47087329626083374,
                "z": -0.12879467010498047
            },
            {
                "name": "THUMB_IP",
                "x": 0.5796917676925659,
                "y": 0.35579583048820496,
                "z": -0.07658097892999649
            },
            {
                "name": "THUMB_TIP",
                "x": 0.5957956314086914,
                "y": 0.24065113067626953,
                "z": -0.012826384045183659
            },
            {
                "name": "INDEX_FINGER_MCP",
                "x": 0.4916805922985077,
                "y": 0.41248080134391785,
                "z": 0.09392760694026947
            },
            {
                "name": "INDEX_FINGER_PIP",
                "x": 0.5539088249206543,
                "y": 0.32931265234947205,
                "z": 0.1585657298564911
            },
            {
                "name": "INDEX_FINGER_DIP",
                "x": 0.5905336737632751,
                "y": 0.29161307215690613,
                "z": 0.1688936948776245
            },
            {
                "name": "INDEX_FINGER_TIP",
                "x": 0.6194567084312439,
                "y": 0.27048569917678833,
                "z": 0.1662641018629074
            },
            {
                "name": "MIDDLE_FINGER_MCP",
                "x": 0.5187315344810486,
                "y": 0.4610392451286316,
                "z": 0.2017643004655838
            },
            {
                "name": "MIDDLE_FINGER_PIP",
                "x": 0.6746014356613159,
                "y": 0.42342883348464966,
                "z": 0.24755752086639404
            },
            {
                "name": "MIDDLE_FINGER_DIP",
                "x": 0.8027210235595703,
                "y": 0.4376782774925232,
                "z": 0.19589290022850037
            },
            {
                "name": "MIDDLE_FINGER_TIP",
                "x": 0.9121713042259216,
                "y": 0.45579031109809875,
                "z": 0.15325427055358887
            },
            {
                "name": "RING_FINGER_MCP",
                "x": 0.5387665033340454,
                "y": 0.5093496441841125,
                "z": 0.29028135538101196
            },
            {
                "name": "RING_FINGER_PIP",
                "x": 0.6770423650741577,
                "y": 0.4758145213127136,
                "z": 0.29547473788261414
            },
            {
                "name": "RING_FINGER_DIP",
                "x": 0.7728821039199829,
                "y": 0.4883647859096527,
                "z": 0.20323216915130615
            },
            {
                "name": "RING_FINGER_TIP",
                "x": 0.8527014255523682,
                "y": 0.5090314149856567,
                "z": 0.14004595577716827
            },
            {
                "name": "PINKY_MCP",
                "x": 0.5634706020355225,
                "y": 0.5478693842887878,
                "z": 0.36978840827941895
            },
            {
                "name": "PINKY_PIP",
                "x": 0.6394134163856506,
                "y": 0.5280346870422363,
                "z": 0.35105544328689575
            },
            {
                "name": "PINKY_DIP",
                "x": 0.6751216053962708,
                "y": 0.5552777051925659,
                "z": 0.2840709984302521
            },
            {
                "name": "PINKY_TIP",
                "x": 0.7130035161972046,
                "y": 0.5696030259132385,
                "z": 0.23628664016723633
            }
        ]
    }
]