[
    {
        "handedness": {
            "index": 1,
            "score": 0.936923086643219,
            "label": "Right"
        },
        "landmarks": [
            {
                "name": "WRIST",
                "x": 0.10954409837722778,
                "y": 0.8044553995132446,
                "z": 1.4114471014181618e-06
            },
            {
                "name": "THUMP_CMC",
                "x": 0.15685507655143738,
                "y": 0.6480416655540466,
                "z": -0.08928589522838593
            },
            {
                "name": "THUMB_MCP",
                "x": 0.3267936110496521,
                "y": 0.537621796131134,
                "z": -0.12388325482606888
            },
            {
                "name": "THUMB_IP",
                "x": 0.499969482421875,
                "y": 0.4943547546863556,
                "z": -0.14934399724006653
            },
            {
                "name": "THUMB_TIP",
                "x": 0.6356657147407532,
                "y": 0.4468582272529602,
                "z": -0.17415863275527954
            },
            {
                "name": "INDEX_FINGER_MCP",
                "x": 0.5996308326721191,
                "y": 0.6165722012519836,
                "z": -0.05186202749609947
            },
            {
                "name": "INDEX_FINGER_PIP",
                "x": 0.8072983622550964,
                "y": 0.6071901321411133,
                "z": -0.11301540583372116
            },
            {
                "name": "INDEX_FINGER_DIP",
                "x": 0.9477274417877197,
                "y": 0.6094623804092407,
                "z": -0.17243675887584686
            },
            {
                "name": "INDEX_FINGER_TIP",
                "x": 1.0667662620544434,
                "y": 0.6139024496078491,
                "z": -0.21536195278167725
            },
            {
                "name": "MIDDLE_FINGER_MCP",
                "x": 0.6353414058685303,
                "y": 0.7035642862319946,
                "z": -0.054308343678712845
            },
            {
                "name": "MIDDLE_FINGER_PIP",
                "x": 0.8614791631698608,
                "y": 0.7008468508720398,
                "z": -0.1050444096326828
            },
            {
                "name": "MIDDLE_FINGER_DIP",
                "x": 1.013556718826294,
                "y": 0.7031988501548767,
                "z": -0.15981613099575043
            },
            {
                "name": "MIDDLE_FINGER_TIP",
                "x": 1.139660358428955,
                "y": 0.7052359580993652,
                "z": -0.20090660452842712
            },
            {
                "name": "RING_FINGER_MCP",
                "x": 0.6275888681411743,
                "y": 0.7837789058685303,
                "z": -0.070951908826828
            },
            {
                "name": "RING_FINGER_PIP",
                "x": 0.8454647660255432,
                "y": 0.7834813594818115,
                "z": -0.12411309778690338
            },
            {
                "name": "RING_FINGER_DIP",
                "x": 0.9964982271194458,
                "y": 0.7856312990188599,
                "z": -0.16239453852176666
            },
            {
                "name": "RING_FINGER_TIP",
                "x": 1.127255916595459,
                "y": 0.7902751564979553,
                "z": -0.1896062195301056
            },
            {
                "name": "PINKY_MCP",
                "x": 0.5860892534255981,
                "y": 0.8659065365791321,
                "z": -0.09731648117303848
            },
            {
                "name": "PINKY_PIP",
                "x": 0.7685368657112122,
                "y": 0.8689212203025818,
                "z": -0.14520981907844543
            },
            {
                "name": "PINKY_DIP",
                "x": 0.8963218927383423,
                "y": 0.8697208166122437,
                "z": -0.16653768718242645
            },
            {
                "name": "PINKY_TIP",
                "x": 1.0160293579101562,
                "y": 0.8696495890617371,
                "z": -0.18088240921497345
            }
        ]
    }
]