[
    {
        "handedness": {
            "index": 1,
            "score": 0.98412024974823,
            "label": "Right"
        },
        "landmarks": [
            {
                "name": "WRIST",
                "x": 0,
                "y": 0.7314758896827698,
                "z": 0
            },
            {
                "name": "THUMP_CMC",
                "x": 0,
                "y": 0.7304158210754395,
                "z": 0
            },
            {
                "name": "THUMB_MCP",
                "x": 0,
                "y": 0.6627160310745239,
                "z": 0
            },
            {
                "name": "THUMB_IP",
                "x": 0,
                "y": 0.5386456251144409,
                "z": 0
            },
            {
                "name": "THUMB_TIP",
                "x": 0,
                "y": 0.42407792806625366,
                "z": 0
            },
            {
                "name": "INDEX_FINGER_MCP",
                "x": 0,
                "y": 0.4365524649620056,
                "z": 0
            },
            {
                "name": "INDEX_FINGER_PIP",
                "x": 0,
                "y": 0.30296698212623596,
                "z": 0
            },
            {
                "name": "INDEX_FINGER_DIP",
                "x": 0,
                "y": 0.2799258530139923,
                "z": 0
            },
            {
                "name": "INDEX_FINGER_TIP",
                "x": 0,
                "y": 0.2842842936515808,
                "z": 0
            },
            {
                "name": "MIDDLE_FINGER_MCP",
                "x": 0,
                "y": 0.4289068281650543,
                "z": 0
            },
            {
                "name": "MIDDLE_FINGER_PIP",
                "x": 0,
                "y": 0.334037184715271,
                "z": 0
            },
            {
                "name": "MIDDLE_FINGER_DIP",
                "x": 0,
                "y": 0.4724395275115967,
                "z": 0
            },
            {
                "name": "MIDDLE_FINGER_TIP",
                "x": 0,
                "y": 0.5185658931732178,
                "z": 0
            },
            {
                "name": "RING_FINGER_MCP",
                "x": 0,
                "y": 0.43131011724472046,
                "z": 0
            },
            {
                "name": "RING_FINGER_PIP",
                "x": 0,
                "y": 0.35099726915359497,
                "z": 0
            },
            {
                "name": "RING_FINGER_DIP",
                "x": 0,
                "y": 0.485220342874527,
                "z": 0
            },
            {
                "name": "RING_FINGER_TIP",
                "x": 0,
                "y": 0.5288578867912292,
                "z": 0
            },
            {
                "name": "PINKY_MCP",
                "x": 0,
                "y": 0.44264137744903564,
                "z": 0
            },
            {
                "name": "PINKY_PIP",
                "x": 0,
                "y": 0.37542203068733215,
                "z": 0
            },
            {
                "name": "PINKY_DIP",
                "x": 0,
                "y": 0.47685736417770386,
                "z": 0
            },
            {
                "name": "PINKY_TIP",
                "x": 0,
                "y": 0.5218280553817749,
                "z": 0
            }
        ]
    }
]